easynetsim/__init__.py
easynetsim/network.py
easynetsim-0.2.0.dist-info/METADATA
easynetsim-0.2.0.dist-info/WHEEL
easynetsim-0.2.0.dist-info/RECORD
