Metadata-Version: 2.1
Name: easynetsim
Version: 0.2.0
Summary: A simple network simulator for testing ping and routing
Home-page: https://github.com/denver-code/easynetsim
License: MIT
Author: Ihor Savenko
Author-email: csigorek@gmail.com
Requires-Python: >=3.10,<4.0
Classifier: License :: OSI Approved :: MIT License
Classifier: Programming Language :: Python :: 3
Classifier: Programming Language :: Python :: 3.10
Classifier: Programming Language :: Python :: 3.11
Classifier: Programming Language :: Python :: 3.12
Classifier: Programming Language :: Python :: 3.13
Requires-Dist: networkx (>=3.4.2,<4.0.0)
Project-URL: Repository, https://github.com/denver-code/easynetsim
